b3j0f/__init__.py
b3j0f/conf/version.py
b3j0f/conf/__init__.py
b3j0f/conf/configurable/__init__.py
b3j0f/conf/configurable/log.py
b3j0f/conf/configurable/core.py
b3j0f/conf/configurable/test/__init__.py
b3j0f/conf/configurable/test/log.py
b3j0f/conf/configurable/test/core.py
b3j0f/conf/model/cat.py
b3j0f/conf/model/__init__.py
b3j0f/conf/model/param.py
b3j0f/conf/model/conf.py
b3j0f/conf/model/base.py
b3j0f/conf/model/test/cat.py
b3j0f/conf/model/test/__init__.py
b3j0f/conf/model/test/param.py
b3j0f/conf/model/test/conf.py
b3j0f/conf/model/test/base.py
b3j0f/conf/parser/__init__.py
b3j0f/conf/parser/core.py
b3j0f/conf/parser/resolver/__init__.py
b3j0f/conf/parser/resolver/registry.py
b3j0f/conf/parser/resolver/core.py
b3j0f/conf/parser/resolver/base.py
b3j0f/conf/parser/resolver/test/__init__.py
b3j0f/conf/parser/resolver/test/registry.py
b3j0f/conf/parser/resolver/test/base.py
b3j0f/conf/parser/resolver/lang/__init__.py
b3j0f/conf/parser/resolver/lang/js.py
b3j0f/conf/parser/resolver/lang/py.py
b3j0f/conf/parser/resolver/lang/test/__init__.py
b3j0f/conf/parser/resolver/lang/test/js.py
b3j0f/conf/parser/resolver/lang/test/py.py
b3j0f/conf/parser/test/__init__.py
b3j0f/conf/parser/test/core.py
b3j0f/conf/data/b3j0fconf-configurable.conf
b3j0f/conf/data/b3j0fconf-log.conf
b3j0f/conf/driver/json.py
b3j0f/conf/driver/xml.py
b3j0f/conf/driver/__init__.py
b3j0f/conf/driver/base.py
b3j0f/conf/driver/file/json.py
b3j0f/conf/driver/file/xml.py
b3j0f/conf/driver/file/__init__.py
b3j0f/conf/driver/file/ini.py
b3j0f/conf/driver/file/base.py
b3j0f/conf/driver/file/test/json.py
b3j0f/conf/driver/file/test/xml.py
b3j0f/conf/driver/file/test/__init__.py
b3j0f/conf/driver/file/test/ini.py
b3j0f/conf/driver/file/test/base.py
b3j0f/conf/driver/test/__init__.py
b3j0f/conf/driver/test/base.py
b3j0f.conf-0.3.22.dist-info/metadata.json
b3j0f.conf-0.3.22.dist-info/top_level.txt
b3j0f.conf-0.3.22.dist-info/DESCRIPTION.rst
b3j0f.conf-0.3.22.dist-info/WHEEL
b3j0f.conf-0.3.22.dist-info/METADATA
b3j0f.conf-0.3.22.dist-info/RECORD
