Metadata-Version: 2.0
Name: b3j0f.conf
Version: 0.3.22
Summary: Python object configuration library in reflective and distributed concerns.
Home-page: https://github.com/b3j0f/conf
Author: b3j0f
Author-email: ib3j0f@gmail.com
License: MIT License
Keywords: conf,configuration,configurable,class,ini,json,xml,tools,property,dynamic,reflection,reflect,runtime,reflectivity
Platform: UNKNOWN
Classifier: Development Status :: 4 - Beta
Classifier: License :: OSI Approved :: MIT License
Classifier: Natural Language :: French
Classifier: Operating System :: OS Independent
Classifier: Topic :: Utilities
Classifier: Topic :: Software Development
Classifier: Intended Audience :: Developers
Classifier: Programming Language :: Python
Classifier: Programming Language :: Python :: 2.6
Classifier: Programming Language :: Python :: 2.7
Classifier: Programming Language :: Python :: 3
Classifier: Programming Language :: Python :: 3.0
Classifier: Programming Language :: Python :: 3.1
Classifier: Programming Language :: Python :: 3.2
Classifier: Programming Language :: Python :: 3.3
Classifier: Programming Language :: Python :: 3.4
Classifier: Programming Language :: Python :: 3.5
Classifier: Programming Language :: Python :: Implementation :: CPython
Requires-Dist: b3j0f.utils
Requires-Dist: b3j0f.annotation
Requires-Dist: six
